{"jeweled dice": {"value": 0, "info": "bone dice set with jewels. probably magic", "weight": 0, "quantity": 1}, "gold": {"value": 1, "info": "small gold pieces used to purchase things", "weight": 0, "quantity": 111}, "thieve's tools": {"value": 20, "info": "tools used to thieve, +2 bonus when opening a lock or trap", "weight": 1, "quantity": 1}, "arrows": {"value": 0, "info": "just regular arrows", "weight": 0.1, "quantity": 30}, "book of necromancy": {"value": 0, "info": "Book of the undead and stuff", "weight": 1, "quantity": 1}, "dagger": {"value": 1, "info": "1d4, regular dagger", "weight": 0.5, "quantity": 2}, "shortbow": {"value": 25, "info": "1d8, shoots arrows with range of 15/30", "weight": 3, "quantity": 1}, "adventurer's kit": {"value": 15, "info": "backpack, bedroll, flint/steel, rations, rope(50ft), sunrods(2), waterskin", "weight": 33, "quantity": 1}, "leather armor": {"value": 25, "info": "light armor, AC + dex + 2", "weight": 15, "quantity": 1}}
